shipyard_azureblob/__init__.py
shipyard_azureblob/azureblob.py
shipyard_azureblob/cli/__init__.py
shipyard_azureblob/cli/authtest.py
shipyard_azureblob/cli/download.py
shipyard_azureblob/cli/move.py
shipyard_azureblob/cli/remove.py
shipyard_azureblob/cli/upload.py
shipyard_azureblob/exceptions.py
shipyard_azureblob-0.2.1.dist-info/METADATA
shipyard_azureblob-0.2.1.dist-info/WHEEL
shipyard_azureblob-0.2.1.dist-info/RECORD
